{
  "project_info": {
    "project_number": "625131481057",
    "firebase_url": "https://flash-2019.firebaseio.com",
    "project_id": "flash-2019",
    "storage_bucket": "flash-2019.appspot.com"
  },
  "client": [
    {
      "client_info": {
        "mobilesdk_app_id": "1:625131481057:android:b1d9fd376d647281",
        "android_client_info": {
          "package_name": "com.example.mayankagarwal.dblog"
        }
      },
      "oauth_client": [
        {
          "client_id": "625131481057-87mv26b3hac7cvo8kv3nak37vd5eqhtl.apps.googleusercontent.com",
          "client_type": 1,
          "android_info": {
            "package_name": "com.example.mayankagarwal.dblog",
            "certificate_hash": "eb89b5abae7a4eb288d3a69650691d2ea30e5566"
          }
        },
        {
          "client_id": "625131481057-6v8bfhjmntpidhjl6u4d21m6h1mh6vrv.apps.googleusercontent.com",
          "client_type": 3
        }
      ],
      "api_key": [
        {
          "current_key": "API_KEY"
        }
      ],
      "services": {
        "appinvite_service": {
          "other_platform_oauth_client": [
            {
              "client_id": "625131481057-6v8bfhjmntpidhjl6u4d21m6h1mh6vrv.apps.googleusercontent.com",
              "client_type": 3
            }
          ]
        }
      }
    }
  ],
  "configuration_version": "1"
}
